README
setup.cfg
setup.py
ofxhome/__init__.py
ofxhome.egg-info/PKG-INFO
ofxhome.egg-info/SOURCES.txt
ofxhome.egg-info/dependency_links.txt
ofxhome.egg-info/entry_points.txt
ofxhome.egg-info/top_level.txt
ofxhome.egg-info/zip-safe