Metadata-Version: 1.0
Name: ofxhome
Version: 0.3
Summary: ofxhome.com financial institution lookup REST client
Home-page: https://github.com/captin411/ofxhome
Author: David Bartle
Author-email: captindave@gmail.com
License: MIT License
Keywords: ofx,Open Financial Exchange,bank search,ofxhome,ofxhome.com
Platform: UNKNOWN
Classifier: Development Status :: 4 - Beta
Classifier: Intended Audience :: Developers
Classifier: Natural Language :: English
Classifier: Operating System :: OS Independent
Classifier: Programming Language :: Python
Classifier: Topic :: Software Development :: Libraries :: Python Modules
Classifier: Topic :: Utilities
Classifier: License :: OSI Approved :: MIT License
